{
  "dna": [
    [
      17,
      12,
      3,
      4
    ],
    [
      3,
      4,
      5,
      3
    ],
    [
      15,
      6,
      1,
      11
    ],
    [
      4,
      1,
      1,
      4
    ],
    [
      1,
      4,
      7,
      4
    ],
    [
      20,
      1,
      2,
      5
    ],
    [
      1,
      11,
      13,
      8
    ]
  ],
  "reward": 0.5497558138880001,
  "episode": 1,
  "timestamp": "2025-12-02T08:38:29.559796",
  "description": "DNA Architecture:\n--------------------------------------------------\nLayer 1: K=17x17, F=12, S=3, P=4x4\nLayer 2: K=3x3, F=4, S=5, P=3x3\nLayer 3: K=15x15, F=6, S=1, P=11x11\nLayer 4: K=4x4, F=1, S=1, P=4x4\nLayer 5: K=1x1, F=4, S=7, P=4x4\nLayer 6: K=20x20, F=1, S=2, P=5x5\nLayer 7: K=1x1, F=11, S=13, P=8x8"
}